{
  "version": 2,
  "extractor": "papercropper",
  "figures": [
    {
      "url": "assets/figures/arxiv/2606.20842v1/fig-001.webp",
      "caption": "",
      "page": 0,
      "index": 1,
      "width": 1268,
      "height": 433,
      "label": "Figure"
    },
    {
      "url": "assets/figures/arxiv/2606.20842v1/fig-002.webp",
      "caption": "",
      "page": 0,
      "index": 2,
      "width": 577,
      "height": 330,
      "label": "Figure"
    },
    {
      "url": "assets/figures/arxiv/2606.20842v1/fig-003.webp",
      "caption": "",
      "page": 0,
      "index": 3,
      "width": 1264,
      "height": 232,
      "label": "Figure"
    },
    {
      "url": "assets/figures/arxiv/2606.20842v1/fig-004.webp",
      "caption": "",
      "page": 0,
      "index": 4,
      "width": 1261,
      "height": 638,
      "label": "Figure"
    },
    {
      "url": "assets/figures/arxiv/2606.20842v1/fig-005.webp",
      "caption": "",
      "page": 0,
      "index": 5,
      "width": 722,
      "height": 416,
      "label": "Figure"
    },
    {
      "url": "assets/figures/arxiv/2606.20842v1/fig-006.webp",
      "caption": "",
      "page": 0,
      "index": 6,
      "width": 836,
      "height": 357,
      "label": "Figure"
    },
    {
      "url": "assets/figures/arxiv/2606.20842v1/fig-007.webp",
      "caption": "",
      "page": 0,
      "index": 7,
      "width": 1241,
      "height": 426,
      "label": "Figure"
    },
    {
      "url": "assets/figures/arxiv/2606.20842v1/fig-008.webp",
      "caption": "",
      "page": 0,
      "index": 8,
      "width": 1242,
      "height": 982,
      "label": "Figure"
    },
    {
      "url": "assets/figures/arxiv/2606.20842v1/fig-009.webp",
      "caption": "",
      "page": 0,
      "index": 9,
      "width": 1238,
      "height": 708,
      "label": "Figure"
    }
  ]
}