{
  "version": 2,
  "extractor": "pdffigures2",
  "figures": [
    {
      "url": "assets/figures/arxiv/2604.11138v1/fig-001.webp",
      "caption": "TABLE XV: Image Augmentation Operators and Parameters",
      "page": 15,
      "index": 1,
      "width": 520,
      "height": 402
    },
    {
      "url": "assets/figures/arxiv/2604.11138v1/fig-002.webp",
      "caption": "TABLE III: Ablation study of pre-rasterization augmentations under nominal and adversarial conditions for pose estimation. We compare our method with models trained with specific augmentation groups removed. We report Average Distance of Model Points (ADD) in mm and a strict accuracy metric (< 10mm and < 10◦), averaged over 5 random seeds.",
      "page": 7,
      "index": 2,
      "width": 1076,
      "height": 248
    },
    {
      "url": "assets/figures/arxiv/2604.11138v1/fig-003.webp",
      "caption": "TABLE II: Evaluation of learned pose estimator on real-world data under nominal and adversarial lighting. Our method is compared against three baselines: Standard Tiled, Randomized Tiled, and Naive GS rendering. We report Average Distance of Model Points (ADD) in mm and a strict accuracy metric (< 10mm and < 10◦), averaged over 5 random seeds.",
      "page": 7,
      "index": 3,
      "width": 1070,
      "height": 228
    },
    {
      "url": "assets/figures/arxiv/2604.11138v1/fig-004.webp",
      "caption": "TABLE XII: Teacher Policy Architecture and PPO Training Configuration",
      "page": 14,
      "index": 4,
      "width": 520,
      "height": 525
    },
    {
      "url": "assets/figures/arxiv/2604.11138v1/fig-005.webp",
      "caption": "TABLE XI: Domain Randomization Parameters",
      "page": 14,
      "index": 5,
      "width": 516,
      "height": 350
    },
    {
      "url": "assets/figures/arxiv/2604.11138v1/fig-006.webp",
      "caption": "TABLE XIII: Student Policy and Distillation Hyperparameters",
      "page": 14,
      "index": 6,
      "width": 523,
      "height": 592
    },
    {
      "url": "assets/figures/arxiv/2604.11138v1/fig-007.webp",
      "caption": "TABLE XIV: Perception Noise Generator Parameters",
      "page": 14,
      "index": 7,
      "width": 523,
      "height": 246
    },
    {
      "url": "assets/figures/arxiv/2604.11138v1/fig-008.webp",
      "caption": "Fig. 2: Overview of our sim-to-real in-hand reorientation pipeline. We first train a teacher policy in simulation with full state access, then distill it into a recurrent student policy that operates from noisy observations. A monocular RGB pose estimator trained with 3D Gaussian Splatting data provides object poses to the student policy, enabling goal-conditioned dexterous manipulation on a real multi-fingered hand.",
      "page": 3,
      "index": 8,
      "width": 1072,
      "height": 523
    },
    {
      "url": "assets/figures/arxiv/2604.11138v1/fig-009.webp",
      "caption": "TABLE VII: Evaluation of learned pose estimator on real-world data under nominal and adversarial lighting. Our method is compared against three baselines: Standard Tiled, Randomized Tiled, and Naive GS rendering. We report the translation error (in mm) and the rotation error (in degrees), averaged over 5 random seeds.",
      "page": 13,
      "index": 9,
      "width": 1076,
      "height": 224
    },
    {
      "url": "assets/figures/arxiv/2604.11138v1/fig-010.webp",
      "caption": "TABLE X: Observation Space",
      "page": 13,
      "index": 10,
      "width": 516,
      "height": 421
    },
    {
      "url": "assets/figures/arxiv/2604.11138v1/fig-011.webp",
      "caption": "TABLE IX: Reward Terms",
      "page": 13,
      "index": 11,
      "width": 518,
      "height": 238
    },
    {
      "url": "assets/figures/arxiv/2604.11138v1/fig-012.webp",
      "caption": "TABLE VIII: Ablation study of pre-rasterization augmentations under nominal and adversarial conditions for pose estimation. We compare our method with models trained with specific augmentation groups removed. We report the translation error (in mm) and the rotation error (in degrees), averaged over 5 random seeds.",
      "page": 13,
      "index": 12,
      "width": 1076,
      "height": 250
    },
    {
      "url": "assets/figures/arxiv/2604.11138v1/fig-013.webp",
      "caption": "Fig. 6: Rollout sequence of the hand reorienting an object to the target pose. The images are from the robot camera feed.",
      "page": 8,
      "index": 13,
      "width": 512,
      "height": 358
    },
    {
      "url": "assets/figures/arxiv/2604.11138v1/fig-014.webp",
      "caption": "Fig. 7: Top: Temporal evolution of translation and rotation errors during a real-world rollout. Red regions indicate intervals where artificial noise is injected into the pose estimator input. The belief decoder (orange) effectively filters these high-frequency perturbations, maintaining significantly lower error compared to the corrupted input (green). Bottom: Visualization of a specific failure case (corresponding to the blue box in the plot). The belief decoder successfully maintains a stable pose estimate close to the ground truth, effectively rejecting a catastrophic 180◦ flip returned by the pose estimator.",
      "page": 12,
      "index": 14,
      "width": 494,
      "height": 690
    },
    {
      "url": "assets/figures/arxiv/2604.11138v1/fig-015.webp",
      "caption": "Fig. 4: Left: The experimental setup with an RGB camera, an Allegro Hand, and a multi-colored light source for adversarial lighting. Right: The object set displayed under normal lighting (first column) and adversarial lighting (second column).",
      "page": 5,
      "index": 15,
      "width": 512,
      "height": 277
    },
    {
      "url": "assets/figures/arxiv/2604.11138v1/fig-016.webp",
      "caption": "TABLE I: Pre-Rasterization Augmentation Parameters",
      "page": 5,
      "index": 16,
      "width": 522,
      "height": 361
    }
  ]
}